negative_binom/__init__.py
negative_binom/binom.py
negative_binom-0.1.5.dist-info/LICENSE
negative_binom-0.1.5.dist-info/METADATA
negative_binom-0.1.5.dist-info/WHEEL
negative_binom-0.1.5.dist-info/top_level.txt
negative_binom-0.1.5.dist-info/RECORD
