Metadata-Version: 2.2
Name: negative-binom
Version: 0.1.5
Summary: A binomial function that extends the domain of combinations to include negative integers.
Home-page: https://github.com/kaganozer/negative-binom
Author: Kağan Özer
Classifier: Programming Language :: Python :: 3
Classifier: License :: OSI Approved :: MIT License
License-File: LICENSE
Dynamic: author
Dynamic: classifier
Dynamic: description
Dynamic: description-content-type
Dynamic: home-page
Dynamic: summary
